oswdatamodel/__init__.py
oswdatamodel/base.py
oswdatamodel/blade.py
oswdatamodel/fea/__init__.py
oswdatamodel/fea/base.py
oswdatamodel/fea/elements.py
oswdatamodel/fea/nodes.py
oswdatamodel/foundation.py
oswdatamodel/geometry/__init__.py
oswdatamodel/geometry/vectors.py
oswdatamodel/hub.py
oswdatamodel/model.py
oswdatamodel/nacelle.py
oswdatamodel/results/__init__.py
oswdatamodel/results/base.py
oswdatamodel/results/element.py
oswdatamodel/results/results.py
oswdatamodel/results/sp.py
oswdatamodel/rotor.py
oswdatamodel/tower.py
oswdatamodel-0.0.4.dist-info/LICENSE
oswdatamodel-0.0.4.dist-info/METADATA
oswdatamodel-0.0.4.dist-info/WHEEL
oswdatamodel-0.0.4.dist-info/RECORD
