Metadata-Version: 2.1
Name: oswdatamodel
Version: 0.0.4
Summary: Offshore wind turbine structure datamodel written in pydantic.
License: GPL-3.0
Author: Ben Cannell
Requires-Python: >=3.10,<4.0
Classifier: License :: OSI Approved :: GNU General Public License v3 (GPLv3)
Classifier: Programming Language :: Python :: 3
Classifier: Programming Language :: Python :: 3.10
Classifier: Programming Language :: Python :: 3.11
Requires-Dist: black (>=23.9.1,<24.0.0)
Requires-Dist: pydantic (>=2.4.2,<3.0.0)
Requires-Dist: pytest (>=7.4.2,<8.0.0)
